yuque_py/__init__.py
yuque_py/yuque.py
yuque_py/clients/__init__.py
yuque_py/clients/abstract_client.py
yuque_py/clients/client.py
yuque_py/exceptions/__init__.py
yuque_py/exceptions/request_error.py
yuque_py/models/__init__.py
yuque_py/models/doc.py
yuque_py/models/group.py
yuque_py/models/repo.py
yuque_py/models/user.py
yuque_py-0.0.4.dist-info/LICENSE
yuque_py-0.0.4.dist-info/METADATA
yuque_py-0.0.4.dist-info/WHEEL
yuque_py-0.0.4.dist-info/top_level.txt
yuque_py-0.0.4.dist-info/RECORD
