Metadata-Version: 2.1
Name: yuque-py
Version: 0.0.4
Summary: yuque api for python version
Home-page: https://github.com/Zheaoli/yuque-py
Author: Manjusaka
Author-email: me@manjusaka.me
License: MIT License
Platform: UNKNOWN
Classifier: Intended Audience :: Developers
Classifier: License :: OSI Approved :: MIT License
Classifier: Operating System :: MacOS :: MacOS X
Classifier: Operating System :: Microsoft :: Windows
Classifier: Operating System :: POSIX
Classifier: Programming Language :: Python
Classifier: Programming Language :: Python :: 2
Classifier: Programming Language :: Python :: 3
Classifier: Topic :: Software Development :: Libraries :: Python Modules
Classifier: Programming Language :: Python :: Implementation :: PyPy
Classifier: Programming Language :: Python :: Implementation :: CPython
Requires-Python: >=3.6
Requires-Dist: pytest (==5.1.1)
Requires-Dist: pytest-cov (==2.7.1)
Requires-Dist: requests (==2.22.0)
Requires-Dist: requests-mock (==1.6.0)
